print_vis/print_vis.py
print_vis-1.0.1.dist-info/LICENSE
print_vis-1.0.1.dist-info/METADATA
print_vis-1.0.1.dist-info/WHEEL
print_vis-1.0.1.dist-info/top_level.txt
print_vis-1.0.1.dist-info/RECORD
