Metadata-Version: 2.1
Name: print-vis
Version: 1.0.1
Summary: A lightweight python module to visualize progress and other tasks to boost your console window
Home-page: https://github.com/ProgrammingNerdGit/print_vis
Author: Gavin Distaso
Author-email: 
License: MIT
Platform: UNKNOWN
Classifier: License :: OSI Approved :: MIT License
Classifier: Programming Language :: Python :: 3
